py_eusign/__init__.py
py_eusign-1.0.0.dist-info/METADATA
py_eusign-1.0.0.dist-info/WHEEL
py_eusign-1.0.0.dist-info/top_level.txt
py_eusign-1.0.0.dist-info/RECORD
