Metadata-Version: 2.1
Name: py_eusign
Version: 1.0.0
Summary: py_eusign package lock
